mcp_nixos/__init__.py
mcp_nixos/server.py
mcp_nixos-2.2.0.dist-info/METADATA
mcp_nixos-2.2.0.dist-info/WHEEL
mcp_nixos-2.2.0.dist-info/entry_points.txt
mcp_nixos-2.2.0.dist-info/licenses/LICENSE
mcp_nixos-2.2.0.dist-info/RECORD
