Metadata-Version: 2.4
Name: mcp-nixos
Version: 2.2.0
Summary: Model Context Protocol server for NixOS, Home Manager, and nix-darwin resources
Author-email: James Brink <james@utensils.io>
License: MIT
License-File: LICENSE
Classifier: Development Status :: 4 - Beta
Classifier: Intended Audience :: Developers
Classifier: License :: OSI Approved :: MIT License
Classifier: Programming Language :: Python :: 3
Classifier: Programming Language :: Python :: 3.11
Classifier: Programming Language :: Python :: 3.12
Classifier: Programming Language :: Python :: 3.13
Requires-Python: >=3.11
Requires-Dist: beautifulsoup4>=4.13.4
Requires-Dist: fastmcp>=2.11.0
Requires-Dist: requests>=2.32.4
Provides-Extra: dev
Requires-Dist: build>=1.2.2; extra == 'dev'
Requires-Dist: mypy>=1.17.0; extra == 'dev'
Requires-Dist: pytest-asyncio>=1.1.0; extra == 'dev'
Requires-Dist: pytest-cov>=6.2.1; extra == 'dev'
Requires-Dist: pytest-rerunfailures>=15.0; extra == 'dev'
Requires-Dist: pytest-xdist>=3.6.0; extra == 'dev'
Requires-Dist: pytest>=9.0.0; extra == 'dev'
Requires-Dist: ruff>=0.12.4; extra == 'dev'
Requires-Dist: twine>=6.0.1; extra == 'dev'
Requires-Dist: types-beautifulsoup4>=4.12.0.20250516; extra == 'dev'
Requires-Dist: types-requests>=2.32.4; extra == 'dev'
Provides-Extra: win
Requires-Dist: pywin32>=308.0; extra == 'win'
